pytest_aws_fixtures/__init__.py
pytest_aws_fixtures/aws_fixtures.py
pytest_aws_fixtures-3.1.3.dist-info/METADATA
pytest_aws_fixtures-3.1.3.dist-info/WHEEL
pytest_aws_fixtures-3.1.3.dist-info/entry_points.txt
pytest_aws_fixtures-3.1.3.dist-info/licenses/LICENSE
pytest_aws_fixtures-3.1.3.dist-info/RECORD
