Metadata-Version: 2.4
Name: pytest-aws-fixtures
Version: 3.1.3
Summary: A series of fixtures to use in integration tests involving actual AWS services.
License-Expression: MIT
License-File: LICENSE
Author: Ryan Causey
Author-email: ryan.causey@munipal.io
Requires-Python: >=3.9,<4.0
Classifier: Framework :: Pytest
Requires-Dist: boto3 (>=1.34.0,<2.0.0)
Requires-Dist: jsonpath-ng (>=1.6.1,<2.0.0)
Requires-Dist: pytest (>=8.0.0,<10.0.0)
Requires-Dist: tenacity (>=9.0.0,<10.0.0)
